facebook_business/__init__.py
facebook_business/api.py
facebook_business/apiconfig.py
facebook_business/bootstrap.py
facebook_business/crashreporter.py
facebook_business/exceptions.py
facebook_business/exit_codes.py
facebook_business/fb_ca_chain_bundle.crt
facebook_business/mixins.py
facebook_business/session.py
facebook_business/specs.py
facebook_business/typechecker.py
facebook_business/video_uploader.py
facebook_business/adobjects/__init__.py
facebook_business/adobjects/abstractcrudobject.py
facebook_business/adobjects/abstractobject.py
facebook_business/adobjects/abtestposttestactions.py
facebook_business/adobjects/ad.py
facebook_business/adobjects/adaccount.py
facebook_business/adobjects/adaccountaaacompatibleadobjects.py
facebook_business/adobjects/adaccountaaasimilarcampaigns.py
facebook_business/adobjects/adaccountadlimitsinsights.py
facebook_business/adobjects/adaccountadrulescountbytype.py
facebook_business/adobjects/adaccountadruleshistory.py
facebook_business/adobjects/adaccountadsrecommendedaudios.py
facebook_business/adobjects/adaccountadvolume.py
facebook_business/adobjects/adaccountagencyfeeconfig.py
facebook_business/adobjects/adaccountallpaymentmethods.py
facebook_business/adobjects/adaccountamountspenthistory.py
facebook_business/adobjects/adaccountappsetuprequirements.py
facebook_business/adobjects/adaccountaslschedule.py
facebook_business/adobjects/adaccountbankinfolist.py
facebook_business/adobjects/adaccountbillingdatepreference.py
facebook_business/adobjects/adaccountbusinessconstraints.py
facebook_business/adobjects/adaccountcampaignattributionoptioninfo.py
facebook_business/adobjects/adaccountcreationrequest.py
facebook_business/adobjects/adaccountcustomaudiencelimits.py
facebook_business/adobjects/adaccountdefaultdestination.py
facebook_business/adobjects/adaccountdefaultobjective.py
facebook_business/adobjects/adaccountdeliveryestimate.py
facebook_business/adobjects/adaccountdsarecommendations.py
facebook_business-24.0.0.dist-info/licenses/LICENSE
facebook_business-24.0.0.dist-info/METADATA
facebook_business-24.0.0.dist-info/WHEEL
facebook_business-24.0.0.dist-info/top_level.txt
facebook_business-24.0.0.dist-info/RECORD
