Metadata-Version: 2.4
Name: facebook_business
Version: 24.0.0
Summary: Facebook Business SDK
Home-page: https://github.com/facebook/facebook-python-business-sdk
Download-URL: https://github.com/facebook/facebook-python-business-sdk/tarball/24.0.0
Author: Facebook
Author-email: shuotian@meta.com
License: LICENSE.txt
License-File: LICENSE
Requires-Dist: requests>=2.3.0
Requires-Dist: six>=1.7.3
Requires-Dist: curlify>=2.1.0
Requires-Dist: pycountry>=19.8.18
Requires-Dist: aiohttp; python_version >= "3.5.3"
Dynamic: author
Dynamic: author-email
Dynamic: description
Dynamic: description-content-type
Dynamic: download-url
Dynamic: home-page
Dynamic: license
Dynamic: license-file
Dynamic: requires-dist
Dynamic: summary
